microhttp_restful/__init__.py
microhttp_restful/application.py
microhttp_restful/base_model.py
microhttp_restful/controllers.py
microhttp_restful/field.py
microhttp_restful/metadata.py
microhttp_restful/validation.py
microhttp_restful/mixins/__init__.py
microhttp_restful/mixins/activation.py
microhttp_restful/mixins/created.py
microhttp_restful/mixins/defaults_mixin.py
microhttp_restful/mixins/filtering.py
microhttp_restful/mixins/modified.py
microhttp_restful/mixins/ordering.py
microhttp_restful/mixins/pagination.py
microhttp_restful/mixins/soft_delete.py
microhttp_restful/tests/__init__.py
microhttp_restful/tests/test_activation_mixin.py
microhttp_restful/tests/test_application.py
microhttp_restful/tests/test_base_model.py
microhttp_restful/tests/test_created_minxin.py
microhttp_restful/tests/test_defaults_mixin.py
microhttp_restful/tests/test_documentation.py
microhttp_restful/tests/test_filtering_mixin.py
microhttp_restful/tests/test_jsonpatch.py
microhttp_restful/tests/test_modified_mixin.py
microhttp_restful/tests/test_ordering_mixin.py
microhttp_restful/tests/test_orm.py
microhttp_restful/tests/test_pagination_mixin.py
microhttp_restful/tests/test_prevent_form.py
microhttp_restful/tests/test_soft_delete_mixin.py
microhttp_restful/tests/test_validation_blacklist.py
microhttp_restful/tests/test_validation_by_model.py
microhttp_restful/tests/test_validation_exact.py
microhttp_restful/tests/test_validation_exclude.py
microhttp_restful/tests/test_validation_filter.py
microhttp_restful/tests/test_validation_pattern.py
microhttp_restful/tests/test_validation_requires.py
microhttp_restful/tests/test_validation_types.py
microhttp_restful/tests/test_validation_whitelist.py
microhttp_restful/tests/helpers/__init__.py
microhttp_restful/tests/helpers/fake_auth.py
microhttp_restful/tests/helpers/mock_application.py
microhttp_restful/tests/helpers/testcases.py
microhttp_restful-0.8.7.dist-info/LICENSE
microhttp_restful-0.8.7.dist-info/METADATA
microhttp_restful-0.8.7.dist-info/WHEEL
microhttp_restful-0.8.7.dist-info/top_level.txt
microhttp_restful-0.8.7.dist-info/RECORD
