Metadata-Version: 2.1
Name: microhttp-restful
Version: 0.8.7
Summary: A tool-chain for create RESTful web applications.
Home-page: http://github.com/meyt/microhttp-restful
Author: Mahdi Ghanea.g
Author-email: contact@meyti.ir
License: MIT
Platform: UNKNOWN
Classifier: Environment :: Web Environment
Classifier: Intended Audience :: Developers
Classifier: Natural Language :: English
Classifier: Operating System :: OS Independent
Classifier: Programming Language :: Python :: 3.6
Classifier: Topic :: Software Development
Classifier: Topic :: Internet :: WWW/HTTP
Classifier: Topic :: Internet :: WWW/HTTP :: Dynamic Content
Classifier: Topic :: Internet :: WWW/HTTP :: WSGI :: Application
Classifier: Topic :: Software Development :: Libraries
Classifier: Topic :: Software Development :: Libraries :: Python Modules
Requires-Dist: pytz
Requires-Dist: microhttp (~=0.14.0)
Requires-Dist: sqlalchemy-dict (>=0.7.0)
Requires-Dist: webtest-docgen
